flake8_plus/__init__.py
flake8_plus/config.py
flake8_plus/defaults.py
flake8_plus/exceptions.py
flake8_plus/plugin.py
flake8_plus/problem.py
flake8_plus/version.py
flake8_plus/visitors/__init__.py
flake8_plus/visitors/base_visitor.py
flake8_plus/visitors/plu001_visitor.py
flake8_plus/visitors/plu002_visitor.py
flake8_plus/visitors/plu003_visitor.py
tests/__init__.py
tests/test_plugin.py
tests/visitors/__init__.py
tests/visitors/test_plu001_visitor.py
tests/visitors/test_plu002_visitor.py
tests/visitors/test_plu003_visitor.py
tests/visitors/util.py
flake8_plus-0.5.1.dist-info/LICENSE
flake8_plus-0.5.1.dist-info/METADATA
flake8_plus-0.5.1.dist-info/WHEEL
flake8_plus-0.5.1.dist-info/entry_points.txt
flake8_plus-0.5.1.dist-info/top_level.txt
flake8_plus-0.5.1.dist-info/RECORD
